pureconnection/__init__.py
pureconnection/_connection.py
pureconnection/_database.py
pureconnection/_utils.py
pureconnection-4.2.0.dist-info/METADATA
pureconnection-4.2.0.dist-info/WHEEL
pureconnection-4.2.0.dist-info/top_level.txt
pureconnection-4.2.0.dist-info/RECORD
